odoo/addons/account_move_reversal_choose_method/README.rst
odoo/addons/account_move_reversal_choose_method/__init__.py
odoo/addons/account_move_reversal_choose_method/__manifest__.py
odoo/addons/account_move_reversal_choose_method/i18n/account_move_reversal_choose_method.pot
odoo/addons/account_move_reversal_choose_method/i18n/it.po
odoo/addons/account_move_reversal_choose_method/readme/CONTRIBUTORS.rst
odoo/addons/account_move_reversal_choose_method/readme/DESCRIPTION.rst
odoo/addons/account_move_reversal_choose_method/static/description/icon.png
odoo/addons/account_move_reversal_choose_method/static/description/index.html
odoo/addons/account_move_reversal_choose_method/wizard/account_move_reversal_view.xml
odoo14_addon_account_move_reversal_choose_method-14.0.1.0.1.dev5.dist-info/METADATA
odoo14_addon_account_move_reversal_choose_method-14.0.1.0.1.dev5.dist-info/WHEEL
odoo14_addon_account_move_reversal_choose_method-14.0.1.0.1.dev5.dist-info/top_level.txt
odoo14_addon_account_move_reversal_choose_method-14.0.1.0.1.dev5.dist-info/RECORD
